LICENSE
README.md
fastapi_tenants/__init__.py
fastapi_tenants/py.typed
fastapi_tenants/version.py
fastapi_tenants-0.0.2.dist-info/METADATA
fastapi_tenants-0.0.2.dist-info/WHEEL
fastapi_tenants-0.0.2.dist-info/entry_points.txt
fastapi_tenants-0.0.2.dist-info/licenses/LICENSE
fastapi_tenants-0.0.2.dist-info/RECORD
